hyperscale/kite/__init__.py
hyperscale/kite/accessanalyzer.py
hyperscale/kite/acm.py
hyperscale/kite/acm_pca.py
hyperscale/kite/apigateway.py
hyperscale/kite/appsync.py
hyperscale/kite/backup.py
hyperscale/kite/cli.py
hyperscale/kite/cloudfront.py
hyperscale/kite/cloudtrail.py
hyperscale/kite/cognito.py
hyperscale/kite/collect.py
hyperscale/kite/conditions.py
hyperscale/kite/config.py
hyperscale/kite/configservice.py
hyperscale/kite/core.py
hyperscale/kite/data.py
hyperscale/kite/detective.py
hyperscale/kite/dynamodb.py
hyperscale/kite/ec2.py
hyperscale/kite/ecs.py
hyperscale/kite/efs.py
hyperscale/kite/eks.py
hyperscale/kite/elbv2.py
hyperscale/kite/guardduty.py
hyperscale/kite/helpers.py
hyperscale/kite/iam.py
hyperscale/kite/identity_center.py
hyperscale/kite/identity_store.py
hyperscale/kite/inspector2.py
hyperscale/kite/kms.py
hyperscale/kite/lambda_.py
hyperscale/kite/logs.py
hyperscale/kite/models.py
hyperscale/kite/networkfirewall.py
hyperscale/kite/organizations.py
hyperscale/kite/prowler.py
hyperscale/kite/rds.py
hyperscale/kite/redshift.py
hyperscale/kite/report.py
hyperscale/kite/route53resolver.py
hyperscale/kite/s3.py
hyperscale/kite/sagemaker.py
hyperscale/kite/secretsmanager.py
hyperscale/kite/securityhub.py
hyperscale/kite/sns.py
hyperscale/kite/sqs.py
hyperscale/kite/ssm.py
hyperscale/kite/sts.py
hyperscale/kite/ui.py
hyperscale/kite/wafv2.py
hyperscale/kite/checks/__init__.py
hyperscale/kite/checks/access_management_lifecycle.py
hyperscale/kite/checks/access_management_lifecycle_implemented.py
hyperscale/kite/checks/account_separation.py
hyperscale/kite/checks/accurate_account_contact_details.py
hyperscale/kite/checks/active_external_access_analyzer.py
hyperscale/kite/checks/active_unused_access_analyzer.py
hyperscale/kite/checks/admin_privileges_are_restricted.py
hyperscale/kite/checks/air_gapped_backup_vault.py
hyperscale/kite/checks/api_gateway_logging_enabled.py
hyperscale/kite/checks/approval_process_for_resource_sharing.py
hyperscale_kite-0.5.4.dist-info/METADATA
hyperscale_kite-0.5.4.dist-info/WHEEL
hyperscale_kite-0.5.4.dist-info/entry_points.txt
hyperscale_kite-0.5.4.dist-info/licenses/LICENSE
hyperscale_kite-0.5.4.dist-info/RECORD
