Metadata-Version: 2.4
Name: hyperscale-kite
Version: 0.5.4
Summary: A tool for AWS security assessments
Project-URL: repository, https://github.com/hyperscale-consulting/kite
Author-email: Andy Caine <andy@hyperscale.consulting>, Henry Addico <henry@hyperscale.consulting>
License-Expression: MIT
License-File: LICENSE
Requires-Python: >=3.10
Requires-Dist: boto3>=1.38.0
Requires-Dist: click>=8.0.0
Requires-Dist: dacite>=1.9.0
Requires-Dist: prompt-toolkit>=3.0.0
Requires-Dist: pyyaml>=6.0.0
Requires-Dist: rich>=10.0.0
